<?xml version="1.0" encoding="UTF-8"?>
<objects serializationModel="Studio.02.01.00">
	<object class="AudioFile" id="{a4fe8917-9cce-4788-a2d0-98effe327b18}">
		<property name="assetPath">
			<value>Karton/KartonAblegen.ogg</value>
		</property>
		<property name="frequencyInKHz">
			<value>48</value>
		</property>
		<property name="channelCount">
			<value>2</value>
		</property>
		<property name="length">
			<value>0.43304166666666666</value>
		</property>
		<relationship name="masterAssetFolder">
			<destination>{9befab32-3d6f-4a44-8232-80253b4ea8fc}</destination>
		</relationship>
	</object>
</objects>
